resty/__init__.py
resty/__version__.py
resty/clients/__init__.py
resty/clients/httpx/__init__.py
resty/clients/httpx/clients.py
resty/clients/types.py
resty/constants.py
resty/enums.py
resty/exceptions.py
resty/ext/__init__.py
resty/ext/django/__init__.py
resty/ext/django/middlewares/__init__.py
resty/ext/django/middlewares/pagination/__init__.py
resty/ext/django/middlewares/pagination/constants.py
resty/ext/django/middlewares/pagination/middlewares.py
resty/managers/__init__.py
resty/managers/builders.py
resty/managers/managers.py
resty/managers/types.py
resty/middlewares/__init__.py
resty/middlewares/managers.py
resty/middlewares/status.py
resty/middlewares/types.py
resty/serializers/__init__.py
resty/serializers/serializers.py
resty/serializers/types.py
resty/types.py
resty_client-0.0.6.dist-info/LICENSE
resty_client-0.0.6.dist-info/METADATA
resty_client-0.0.6.dist-info/WHEEL
resty_client-0.0.6.dist-info/RECORD
