Metadata-Version: 2.1
Name: resty-client
Version: 0.0.6
Summary: RestyClient is a simple, easy-to-use Python library for interacting with REST APIs using Pydantic's powerful data validation and deserialization tools.
License: MIT
Author: CrazyProger1
Author-email: crazyproger1@gmail.com
Requires-Python: >=3.12,<4.0
Classifier: License :: OSI Approved :: MIT License
Classifier: Programming Language :: Python :: 3
Classifier: Programming Language :: Python :: 3.12
Requires-Dist: pydantic (>=2.5.3,<3.0.0)
